{
  "company": "Wissen Technology",
  "stats": {
    "totalProblems": 3,
    "uniqueProblems": 3,
    "avgFrequency": 96.0375,
    "avgAcceptanceRate": 0.5837998592240531,
    "difficultyDistribution": {
      "EASY": 4,
      "MEDIUM": 4,
      "HARD": 0,
      "UNKNOWN": 0
    }
  },
  "problems": [
    {
      "title": "Longest Consecutive Sequence",
      "titleSlug": "longest-consecutive-sequence",
      "difficulty": "MEDIUM",
      "frequency": 100.0,
      "acceptanceRate": 0.470392322552122,
      "link": "https://leetcode.com/problems/longest-consecutive-sequence",
      "topics": [
        "Array",
        "Hash Table",
        "Union Find"
      ],
      "timeframe": "6m",
      "timeframes": [
        "6m",
        "all",
        "30d",
        "3m"
      ]
    },
    {
      "title": "Two Sum",
      "titleSlug": "two-sum",
      "difficulty": "EASY",
      "frequency": 100.0,
      "acceptanceRate": 0.5578041336158984,
      "link": "https://leetcode.com/problems/two-sum",
      "topics": [
        "Array",
        "Hash Table"
      ],
      "timeframe": "6m+",
      "timeframes": [
        "6m+",
        "all"
      ]
    },
    {
      "title": "Reverse Words in a String III",
      "titleSlug": "reverse-words-in-a-string-iii",
      "difficulty": "EASY",
      "frequency": 89.7,
      "acceptanceRate": 0.836610711561557,
      "link": "https://leetcode.com/problems/reverse-words-in-a-string-iii",
      "topics": [
        "Two Pointers",
        "String"
      ],
      "timeframe": "6m+",
      "timeframes": [
        "6m+",
        "all"
      ]
    }
  ],
  "topTopics": [
    "Array",
    "Hash Table",
    "Union Find",
    "Two Pointers",
    "String"
  ]
}